{"credit":"Made with Blockbench","textures":{"0":"custom/furniture/grand_father_clock","1":"custom/furniture/pendulum","particle":"custom/furniture/grand_father_clock"},"elements":[{"from":[13.5,32,3.5],"to":[2.5,29,2.5],"rotation":{"angle":0,"axis":"y","origin":[8,25,8]},"faces":{"east":{"uv":[2.75,0,3,0.75],"rotation":180,"texture":"#0"},"south":{"uv":[0.25,0,3,0.75],"rotation":180,"texture":"#0"},"west":{"uv":[2.75,0,3,0.75],"rotation":180,"texture":"#0"}}},{"from":[2.5,29,2.5],"to":[13.5,32,3.5],"rotation":{"angle":0,"axis":"y","origin":[8,25,8]},"faces":{"north":{"uv":[0.25,0,3,0.75],"texture":"#0"},"east":{"uv":[2.75,0,3,0.75],"texture":"#0"},"west":{"uv":[2.75,0,3,0.75],"texture":"#0"}}},{"from":[2.5,17,2.5],"to":[13.5,29,13.5],"rotation":{"angle":0,"axis":"y","origin":[8,25,8]},"faces":{"north":{"uv":[0.25,0.75,3,3.75],"texture":"#0"},"east":{"uv":[3.5,0.75,6.25,3.75],"texture":"#0"},"south":{"uv":[3.5,0.75,6.25,3.75],"texture":"#0"},"west":{"uv":[3.5,0.75,6.25,3.75],"texture":"#0"},"up":{"uv":[3.5,1,6.25,3.75],"texture":"#0"},"down":{"uv":[3.5,1,6.25,3.75],"texture":"#0"}}},{"from":[11.5,-10,2.5],"to":[13.5,15,13.5],"rotation":{"angle":0,"axis":"y","origin":[8,25,8]},"faces":{"north":{"uv":[0.25,4.25,0.75,10.5],"texture":"#0"},"east":{"uv":[3.5,3.75,6.25,10],"texture":"#0"},"south":{"uv":[0.75,4.25,0.25,10.5],"texture":"#0"},"west":{"uv":[0.25,4.25,3,10.5],"texture":"#0"}}},{"from":[2.5,-10,2.5],"to":[4.5,15,13.5],"rotation":{"angle":0,"axis":"y","origin":[8,25,8]},"faces":{"north":{"uv":[0.75,4.25,0.25,10.5],"texture":"#0"},"east":{"uv":[0.25,4.25,3,10.5],"texture":"#0"},"south":{"uv":[0.25,4.25,0.75,10.5],"texture":"#0"},"west":{"uv":[3.5,3.75,6.25,10],"texture":"#0"}}},{"from":[1.5,15,1.5],"to":[14.5,17,14.5],"faces":{"north":{"uv":[0,3.75,3.25,4.25],"texture":"#0"},"east":{"uv":[0,3.75,3.25,4.25],"texture":"#0"},"south":{"uv":[0,3.75,3.25,4.25],"texture":"#0"},"west":{"uv":[0,3.75,3.25,4.25],"texture":"#0"},"up":{"uv":[3.5,10.25,6.75,13.5],"texture":"#0"},"down":{"uv":[3.5,10.25,6.75,13.5],"texture":"#0"}}},{"from":[1.5,-16,1.5],"to":[14.5,-9,14.5],"faces":{"north":{"uv":[0,10.25,3.25,12],"texture":"#0"},"east":{"uv":[0,10.25,3.25,12],"texture":"#0"},"south":{"uv":[0,10.25,3.25,12],"texture":"#0"},"west":{"uv":[0,10.25,3.25,12],"texture":"#0"},"up":{"uv":[3.5,10.25,6.75,13.5],"texture":"#0"},"down":{"uv":[3.5,10.25,6.75,13.5],"texture":"#0"}}},{"from":[4.5,-10,8.5],"to":[11.5,15,13.5],"faces":{"north":{"uv":[0.75,4.25,2.5,10.5],"texture":"#0"},"south":{"uv":[4,3.75,5.75,10],"texture":"#0"}}},{"from":[4.5,-10,4.5],"to":[11.5,15,4.5],"faces":{"north":{"uv":[0,0,3.5,12.5],"texture":"#1"},"south":{"uv":[3.5,0,0,12.5],"texture":"#1"}}},{"from":[4.5,-9,2.5],"to":[11.5,-6,2.5],"faces":{"north":{"uv":[6.5,9.5,8.25,10.25],"texture":"#0"},"south":{"uv":[6.5,9.5,8.25,10.25],"texture":"#0"}}}],"display":{"thirdperson_righthand":{"rotation":[41,33,0],"translation":[0,0.75,0],"scale":[0.2,0.2,0.2]},"thirdperson_lefthand":{"rotation":[41,33,0],"translation":[0,0.75,0],"scale":[0.2,0.2,0.2]},"firstperson_righthand":{"rotation":[0,108,0],"translation":[26,-8.25,-20]},"firstperson_lefthand":{"rotation":[0,108,0],"translation":[26,-8.25,-20]},"ground":{"translation":[0,4.5,0],"scale":[0.2,0.2,0.2]},"gui":{"rotation":[30,135,0],"translation":[0,0.5,0],"scale":[0.35,0.35,0.35]},"head":{"translation":[0,32.25,0],"scale":[1.2,1.2,1.2]},"fixed":{"rotation":[-90,0,0],"translation":[0,0,-16],"scale":[2,2,2]}},"groups":[{"name":"group","origin":[8,8,8],"children":[0,1,2,3,4,5,6]},7,8,9]}